causaldid/__init__.py
causaldid/_version.py
causaldid/data.py
causaldid/utils.py
causaldid/_data/__init__.py
causaldid/_data/ehec_data.pkl.gz
causaldid/_data/mpdta_long.pkl.gz
causaldid/_data/nsw_long.pkl.gz
causaldid/did/README.md
causaldid/did/__init__.py
causaldid/did/aggte.py
causaldid/did/aggte_obj.py
causaldid/did/att_gt.py
causaldid/did/compute_aggte.py
causaldid/did/compute_att_gt.py
causaldid/did/mboot.py
causaldid/did/multiperiod_obj.py
causaldid/did/preprocess_did.py
causaldid/did/plots/__init__.py
causaldid/did/plots/core.py
causaldid/did/plots/methods.py
causaldid/did/preprocess/__init__.py
causaldid/did/preprocess/builders.py
causaldid/did/preprocess/constants.py
causaldid/did/preprocess/models.py
causaldid/did/preprocess/tensors.py
causaldid/did/preprocess/transformers.py
causaldid/did/preprocess/validators.py
causaldid/did2s/README.md
causaldid/did2s/__init__.py
causaldid/didbacon/README.md
causaldid/didbacon/__init__.py
causaldid/didcomp/README.md
causaldid/didcomp/__init__.py
causaldid/didcont/README.md
causaldid/didcont/__init__.py
causaldid/didhonest/README.md
causaldid/didhonest/__init__.py
causaldid/didhonest/arp_no_nuisance.py
causaldid/didhonest/arp_nuisance.py
causaldid/didhonest/bounds.py
causaldid/didhonest/conditional.py
causaldid/didhonest/fixed_length_ci.py
causaldid/didhonest/honest_did.py
causaldid/didhonest/numba.py
causaldid/didhonest/sensitivity.py
causaldid/didhonest/utils.py
causaldid/didhonest/wrappers.py
causaldid/didhonest/delta/__init__.py
causaldid/didhonest/delta/base.py
causaldid/didhonest/delta/rm/__init__.py
causaldid/didhonest/delta/rm/rm.py
causaldid/didhonest/delta/rm/rmb.py
causaldid/didhonest/delta/rm/rmm.py
causaldid/didhonest/delta/sd/__init__.py
causaldid/didhonest/delta/sd/sd.py
causaldid/didhonest/delta/sd/sdb.py
causaldid/didhonest/delta/sd/sdm.py
causaldid/didhonest/delta/sdrm/__init__.py
causaldid/didhonest/delta/sdrm/sdrm.py
causaldid/didhonest/delta/sdrm/sdrmb.py
causaldid/didhonest/delta/sdrm/sdrmm.py
causaldid-0.0.1.dist-info/licenses/LICENSE
causaldid-0.0.1.dist-info/WHEEL
causaldid-0.0.1.dist-info/METADATA
causaldid-0.0.1.dist-info/RECORD
